MANIFEST.in
README.rst
setup.cfg
setup.py
OneSignalPythonSDK.egg-info/PKG-INFO
OneSignalPythonSDK.egg-info/SOURCES.txt
OneSignalPythonSDK.egg-info/dependency_links.txt
OneSignalPythonSDK.egg-info/requires.txt
OneSignalPythonSDK.egg-info/top_level.txt
flask_app/__init__.py
flask_app/app.py
onesignalsdk/__init__.py
onesignalsdk/one_signal_sdk.py