Metadata-Version: 1.1
Name: OneSignalPythonSDK
Version: 0.1
Summary: A Python SDK for OneSignal (http://onesignal.com)
Home-page: https://github.com/gettalent/one-signal-python-sdk
Author: Waqas Younas, Zohaib Ijaz
Author-email: waqas.younas@gmail.com, mzohaib.qc@gmail.com
License: UNKNOWN
Keywords: onesignal,onesignalsdk,sdk
Platform: UNKNOWN
Classifier: Development Status :: 3 - Alpha
Classifier: Intended Audience :: Developers
Classifier: Topic :: Internet
Classifier: Topic :: Software Development :: Libraries
Classifier: Topic :: Software Development :: Libraries :: Python Modules
Classifier: Programming Language :: Python :: 2.7
